aiobravado/__init__.py
aiobravado/client.py
aiobravado/compat.py
aiobravado/config_defaults.py
aiobravado/docstring_property.py
aiobravado/exception.py
aiobravado/http_client.py
aiobravado/http_future.py
aiobravado/swagger_model.py
aiobravado/warning.py
aiobravado-0.9.3.dist-info/DESCRIPTION.rst
aiobravado-0.9.3.dist-info/METADATA
aiobravado-0.9.3.dist-info/RECORD
aiobravado-0.9.3.dist-info/WHEEL
aiobravado-0.9.3.dist-info/metadata.json
aiobravado-0.9.3.dist-info/top_level.txt
