Metadata-Version: 2.0
Name: aiobravado
Version: 0.9.3
Summary: Async library for accessing Swagger-enabled APIs
Home-page: https://github.com/sjaensch/aiobravado
Author: Stephan Jaensch, Digium, Inc. and Yelp, Inc.
Author-email: sj@sjaensch.org
License: BSD 3-Clause License
Platform: UNKNOWN
Classifier: Development Status :: 4 - Beta
Classifier: Intended Audience :: Developers
Classifier: Topic :: Software Development :: Libraries :: Python Modules
Classifier: License :: OSI Approved :: BSD License
Classifier: Operating System :: OS Independent
Classifier: Programming Language :: Python :: 3.5
Classifier: Programming Language :: Python :: 3.6
Provides-Extra: aiohttp_extras
Requires-Dist: bravado-asyncio (<1.1.0,>=0.4.0)
Requires-Dist: bravado-core (>=4.11.0)
Requires-Dist: msgpack-python
Requires-Dist: python-dateutil
Requires-Dist: pyyaml
Provides-Extra: aiohttp_extras
Requires-Dist: aiodns; extra == 'aiohttp_extras'
Requires-Dist: cchardet; extra == 'aiohttp_extras'
